simlify/__init__.py
simlify/data/__init__.py
simlify/data/atomistic.py
simlify/data/backends/__init__.py
simlify/data/backends/_parquet.py
simlify/data/backends/_zarr.py
simlify/data/store.py
simlify/simulation/__init__.py
simlify/simulation/amber/__init__.py
simlify/simulation/amber/contexts.py
simlify/simulation/amber/prep.py
simlify/simulation/amber/topo.py
simlify/simulation/contexts.py
simlify/simulation/prep.py
simlify/simulation/topo.py
simlify/structure/__init__.py
simlify/structure/pdb/__init__.py
simlify/structure/pdb/modify/__init__.py
simlify/structure/pdb/modify/names.py
simlify/structure/pdb/modify/numbering.py
simlify/structure/pdb/modify/orientation.py
simlify/structure/pdb/modify/positioning.py
simlify/structure/pdb/utils.py
simlify/structure/select.py
simlify/structure/solvent.py
simlify/structure/structure.py
simlify/utils.py
simlify-0.0.0.post76.dist-info/LICENSE.md
simlify-0.0.0.post76.dist-info/METADATA
simlify-0.0.0.post76.dist-info/WHEEL
simlify-0.0.0.post76.dist-info/entry_points.txt
simlify-0.0.0.post76.dist-info/RECORD
