Metadata-Version: 2.1
Name: simlify
Version: 0.0.0.post76
Summary: Simplify your molecular simulation workflow.
License: Apache-2.0
Author: oasci
Author-email: us@oasci.org
Requires-Python: >=3.9,<4.0
Classifier: License :: OSI Approved :: Apache Software License
Classifier: Programming Language :: Python :: 3
Classifier: Programming Language :: Python :: 3.9
Classifier: Programming Language :: Python :: 3.10
Classifier: Programming Language :: Python :: 3.11
Classifier: Programming Language :: Python :: 3.12
Requires-Dist: loguru (>=0.7.2,<0.8.0)
Requires-Dist: mdanalysis (>=2.6.1,<3.0.0)
Requires-Dist: numpy (>=1.26.2,<2.0.0)
Requires-Dist: pint (>=0.23,<0.24)
Requires-Dist: pyarrow (>=15.0.0,<16.0.0)
Requires-Dist: ray (>=2.8.1,<3.0.0)
Requires-Dist: scipy (>=1.11.4,<2.0.0)
Requires-Dist: xarray (>=2023.12.0,<2024.0.0)
Requires-Dist: zarr (>=2.16.1,<3.0.0)
